labs/__init__.py
labs/m1.py
pydvma/__init__.py
pydvma/analysis.py
pydvma/file.py
pydvma/logdata.py
pydvma/oscilloscope.py
pydvma/plotting.py
pydvma/settings.py
pydvma-0.1.dev1.dist-info/METADATA
pydvma-0.1.dev1.dist-info/RECORD
pydvma-0.1.dev1.dist-info/WHEEL
pydvma-0.1.dev1.dist-info/top_level.txt
