Metadata-Version: 2.1
Name: pydvma
Version: 0.1.dev1
Summary: UNKNOWN
Home-page: UNKNOWN
Author: UNKNOWN
Author-email: UNKNOWN
License: BSD 3-Clause License
Platform: UNKNOWN
Requires-Dist: distutils
Requires-Dist: numpy
Requires-Dist: scipy
Requires-Dist: time
Requires-Dist: datetime
Requires-Dist: pyqtgraph
Requires-Dist: copy
Requires-Dist: tkinter
Requires-Dist: pyaudio
Requires-Dist: pandas
Requires-Dist: matplotlib
